mittepro/__init__.py
mittepro/api.py
mittepro/client.py
mittepro/mitte_exceptions.py
mittepro/models.py
mittepro/test_variables.py
mittepro/tests.py
mittepro/utils.py
mittepro/apysignature/__init__.py
mittepro/apysignature/query_encoder.py
mittepro/apysignature/signature.py
mittepro-2.4.2.dist-info/LICENSE
mittepro-2.4.2.dist-info/METADATA
mittepro-2.4.2.dist-info/WHEEL
mittepro-2.4.2.dist-info/top_level.txt
mittepro-2.4.2.dist-info/RECORD
