Metadata-Version: 2.1
Name: mittepro
Version: 2.4.2
Summary: MittePro is a powerful marketing tool with features to help companies with their marketing goals and deliver emails from their websites and apps.
Home-page: https://github.com/ThCC/mittepro-py
Author: Thiago Cardoso de Castro
Author-email: thiago.decastro2@gmail.com
License: Apache-2.0
Platform: UNKNOWN
Classifier: Environment :: Web Environment
Classifier: Intended Audience :: Developers
Classifier: License :: OSI Approved :: MIT License
Classifier: Operating System :: OS Independent
Classifier: Programming Language :: Python
Classifier: Programming Language :: Python :: 3
Classifier: Programming Language :: Python :: 3.6
Classifier: Topic :: Software Development :: Libraries
Requires-Python: >=3.5.*, !=3.0.*, !=3.1.*, !=3.2.*, !=3.3.*
Requires-Dist: arrow (>=0.17.0)
Requires-Dist: requests (==2.24.0)
